MANIFEST.in
README.md
setup.cfg
setup.py
TOPSIS_Manpreet_101803562/__init__.py
TOPSIS_Manpreet_101803562/topsis.py
TOPSIS_Manpreet_101803562.egg-info/PKG-INFO
TOPSIS_Manpreet_101803562.egg-info/SOURCES.txt
TOPSIS_Manpreet_101803562.egg-info/dependency_links.txt
TOPSIS_Manpreet_101803562.egg-info/requires.txt
TOPSIS_Manpreet_101803562.egg-info/top_level.txt