Metadata-Version: 2.1
Name: TOPSIS-Manpreet-101803562
Version: 0.1
Summary: We are calculating performances scores for each models which would be ranked and best model is considered
Home-page: https://github.com/mkaur7999/TOPSIS_Manpreet_101803562
Author: Manpreet Kaur
Author-email: mkaur1_be18@thapar.edu
License: MIT
Download-URL: https://github.com/mkaur7999/TOPSIS_Manpreet_101803562/archive/0.1.tar.gz
Platform: UNKNOWN
Classifier: Development Status :: 3 - Alpha
Classifier: Intended Audience :: Developers
Classifier: License :: OSI Approved :: MIT License
Classifier: Programming Language :: Python :: 3
Classifier: Programming Language :: Python :: 3.4
Classifier: Programming Language :: Python :: 3.5
Classifier: Programming Language :: Python :: 3.6
Classifier: Programming Language :: Python :: 3.7
Classifier: Programming Language :: Python :: 3.8
